{
    "page": 3,
    "total_pages": 9,
    "total_items": 419,
    "items": [
        {
            "id": "mvpB4B-s6EI",
            "title": "Street of Chance (1930) WILLIAM POWELLđźŤ•KAY FRANCISđźŤ• FULL MOVIE",
            "url": "https://www.youtube.com/watch?v=mvpB4B-s6EI",
            "duration": 4601.0,
            "view_count": 32649,
            "uploader": "PizzaFlix",
            "category": "classic",
            "channel_tags": [
                "classic",
                "noir",
                "western"
            ],
            "channel_name": "PizzaFlix",
            "thumbnail": "https://i.ytimg.com/vi/mvpB4B-s6EI/hqdefault.jpg?sqp=-oaymwEcCNACELwBSFXyq4qpAw4IARUAAIhCGAFwAcABBg==&rs=AOn4CLBVqTJReibZox3gkFal2wH2sGxvLA",
            "source": "youtube",
            "added_date": "2026-04-16T16:52:02.222457Z"
        },
        {
            "id": "qy7nrvT2WLE",
            "title": "Follow Thru (1930) NANCY CARROLLđźŤ• TECHNICOLORđźŤ• MUSICAL ROM-COM",
            "url": "https://www.youtube.com/watch?v=qy7nrvT2WLE",
            "duration": 5673.0,
            "view_count": 7448,
            "uploader": "PizzaFlix",
            "category": "comedy",
            "channel_tags": [
                "classic",
                "noir",
                "western"
            ],
            "channel_name": "PizzaFlix",
            "thumbnail": "https://i.ytimg.com/vi/qy7nrvT2WLE/hqdefault.jpg?sqp=-oaymwEcCNACELwBSFXyq4qpAw4IARUAAIhCGAFwAcABBg==&rs=AOn4CLAq_NUCuVS4S8qhguj0f3u6WRU9_g",
            "source": "youtube",
            "added_date": "2026-04-16T16:52:02.426260Z"
        },
        {
            "id": "n1k8I4GsM7M",
            "title": "The Trespasser (1929) OSCAR NOMINEEđźŤ• GLORIA SWANSONđźŤ• PRE-CODE TEARJERKER",
            "url": "https://www.youtube.com/watch?v=n1k8I4GsM7M",
            "duration": 5451.0,
            "view_count": 17420,
            "uploader": "PizzaFlix",
            "category": "classic",
            "channel_tags": [
                "classic",
                "noir",
                "western"
            ],
            "channel_name": "PizzaFlix",
            "thumbnail": "https://i.ytimg.com/vi/n1k8I4GsM7M/hqdefault.jpg?sqp=-oaymwEcCNACELwBSFXyq4qpAw4IARUAAIhCGAFwAcABBg==&rs=AOn4CLBwJcxC548sIUMQAUz3-fmBKxdwbQ",
            "source": "youtube",
            "added_date": "2026-04-16T16:52:02.630922Z"
        },
        {
            "id": "07FS1oS3KHg",
            "title": "Hell's Angels (1930) JEAN HARLOWđźŤ•HOWARD HUGHESđźŤ• FULL MOVIE",
            "url": "https://www.youtube.com/watch?v=07FS1oS3KHg",
            "duration": 7880.0,
            "view_count": 20529,
            "uploader": "PizzaFlix",
            "category": "classic",
            "channel_tags": [
                "classic",
                "noir",
                "western"
            ],
            "channel_name": "PizzaFlix",
            "thumbnail": "https://i.ytimg.com/vi/07FS1oS3KHg/hqdefault.jpg?sqp=-oaymwEcCNACELwBSFXyq4qpAw4IARUAAIhCGAFwAcABBg==&rs=AOn4CLD3zzYwEddulk_3UclY6mZu6f2OqQ",
            "source": "youtube",
            "added_date": "2026-04-16T16:52:02.836049Z"
        },
        {
            "id": "r-rnJpiySj8",
            "title": "Romance (MGM, 1930) GRETA GARBOđźŤ• OSCAR NOMINEEđźŤ• FULL MOVIE",
            "url": "https://www.youtube.com/watch?v=r-rnJpiySj8",
            "duration": 4648.0,
            "view_count": 13025,
            "uploader": "PizzaFlix",
            "category": "drama",
            "channel_tags": [
                "classic",
                "noir",
                "western"
            ],
            "channel_name": "PizzaFlix",
            "thumbnail": "https://i.ytimg.com/vi/r-rnJpiySj8/hqdefault.jpg?sqp=-oaymwEcCNACELwBSFXyq4qpAw4IARUAAIhCGAFwAcABBg==&rs=AOn4CLCXyQ_aPAfrBawMIsEo6i1UiJpU1A",
            "source": "youtube",
            "added_date": "2026-04-16T16:52:03.041211Z"
        },
        {
            "id": "L0dV1rWlfp8",
            "title": "The Devil's Holiday (1930) OSCAR NOMINEEđźŤ• NANCY CARROLL",
            "url": "https://www.youtube.com/watch?v=L0dV1rWlfp8",
            "duration": 4574.0,
            "view_count": 23901,
            "uploader": "PizzaFlix",
            "category": "classic",
            "channel_tags": [
                "classic",
                "noir",
                "western"
            ],
            "channel_name": "PizzaFlix",
            "thumbnail": "https://i.ytimg.com/vi/L0dV1rWlfp8/hqdefault.jpg?sqp=-oaymwEcCNACELwBSFXyq4qpAw4IARUAAIhCGAFwAcABBg==&rs=AOn4CLB-5WZtd4zbFLNukhXJM8QpdY192w",
            "source": "youtube",
            "added_date": "2026-04-16T16:52:03.244504Z"
        },
        {
            "id": "T23XFsQoc5M",
            "title": "Spite Marriage (MGM, 1929) BUSTER KEATONđźŤ• DOROTHY SEBASTIANđźŤ• FULL SILENT MOVIE",
            "url": "https://www.youtube.com/watch?v=T23XFsQoc5M",
            "duration": 4583.0,
            "view_count": 3942,
            "uploader": "PizzaFlix",
            "category": "classic",
            "channel_tags": [
                "classic",
                "noir",
                "western"
            ],
            "channel_name": "PizzaFlix",
            "thumbnail": "https://i.ytimg.com/vi/T23XFsQoc5M/hqdefault.jpg?sqp=-oaymwEcCNACELwBSFXyq4qpAw4IARUAAIhCGAFwAcABBg==&rs=AOn4CLC1MAhyFPe9ggKvSVCXlRn3xYH3_g",
            "source": "youtube",
            "added_date": "2026-04-16T16:52:03.446089Z"
        },
        {
            "id": "yatLNfUq7to",
            "title": "Condemned (1929) RONALD COLMANđźŤ•ANN HARDINGđźŤ• FULL MOVIE",
            "url": "https://www.youtube.com/watch?v=yatLNfUq7to",
            "duration": 5223.0,
            "view_count": 12226,
            "uploader": "PizzaFlix",
            "category": "classic",
            "channel_tags": [
                "classic",
                "noir",
                "western"
            ],
            "channel_name": "PizzaFlix",
            "thumbnail": "https://i.ytimg.com/vi/yatLNfUq7to/hqdefault.jpg?sqp=-oaymwEcCNACELwBSFXyq4qpAw4IARUAAIhCGAFwAcABBg==&rs=AOn4CLBul8SzC3UX_6QzfB76xIo1gzGoAA",
            "source": "youtube",
            "added_date": "2026-04-16T16:52:03.650598Z"
        },
        {
            "id": "eSyPuB6ZMVU",
            "title": "Hallelujah (MGM, 1929) KING VIDORđźŤ• OSCAR NOMINEEđźŤ• FULL MOVIE",
            "url": "https://www.youtube.com/watch?v=eSyPuB6ZMVU",
            "duration": 6077.0,
            "view_count": 3857,
            "uploader": "PizzaFlix",
            "category": "classic",
            "channel_tags": [
                "classic",
                "noir",
                "western"
            ],
            "channel_name": "PizzaFlix",
            "thumbnail": "https://i.ytimg.com/vi/eSyPuB6ZMVU/hqdefault.jpg?sqp=-oaymwEcCNACELwBSFXyq4qpAw4IARUAAIhCGAFwAcABBg==&rs=AOn4CLAkSXpzrIfv6XfP9bRb_XLCJ35JzQ",
            "source": "youtube",
            "added_date": "2026-04-16T16:52:03.855706Z"
        },
        {
            "id": "gE8jWh-FJ94",
            "title": "All Quiet on the Western Front (1930) OSCAR WINNERđźŤ• LEWIS MILESTONE",
            "url": "https://www.youtube.com/watch?v=gE8jWh-FJ94",
            "duration": 8094.0,
            "view_count": 6837,
            "uploader": "PizzaFlix",
            "category": "western",
            "channel_tags": [
                "classic",
                "noir",
                "western"
            ],
            "channel_name": "PizzaFlix",
            "thumbnail": "https://i.ytimg.com/vi/gE8jWh-FJ94/hqdefault.jpg?sqp=-oaymwEcCNACELwBSFXyq4qpAw4IARUAAIhCGAFwAcABBg==&rs=AOn4CLB-a8JNzMgaueL6Y7MYl1gAYJOMZg",
            "source": "youtube",
            "added_date": "2026-04-16T16:52:04.060826Z"
        },
        {
            "id": "xB8WVCbiigE",
            "title": "With Byrd at the South Pole (1930) OSCAR WINNERđźŤ• CINEMATOGRAPHYđźŤ• FULL MOVIE",
            "url": "https://www.youtube.com/watch?v=xB8WVCbiigE",
            "duration": 4978.0,
            "view_count": 4404,
            "uploader": "PizzaFlix",
            "category": "classic",
            "channel_tags": [
                "classic",
                "noir",
                "western"
            ],
            "channel_name": "PizzaFlix",
            "thumbnail": "https://i.ytimg.com/vi/xB8WVCbiigE/hqdefault.jpg?sqp=-oaymwEcCNACELwBSFXyq4qpAw4IARUAAIhCGAFwAcABBg==&rs=AOn4CLDsfNC7eSSonq8XB-Zr3DPucFMxJA",
            "source": "youtube",
            "added_date": "2026-04-16T16:52:04.262480Z"
        },
        {
            "id": "ul6pGFRw5jQ",
            "title": "The Big House (MGM, 1930) CHESTER MORRISđźŤ•WALLACE BEERYđźŤ• FULL MOVIE",
            "url": "https://www.youtube.com/watch?v=ul6pGFRw5jQ",
            "duration": 5309.0,
            "view_count": 7806,
            "uploader": "PizzaFlix",
            "category": "classic",
            "channel_tags": [
                "classic",
                "noir",
                "western"
            ],
            "channel_name": "PizzaFlix",
            "thumbnail": "https://i.ytimg.com/vi/ul6pGFRw5jQ/hqdefault.jpg?sqp=-oaymwEcCNACELwBSFXyq4qpAw4IARUAAIhCGAFwAcABBg==&rs=AOn4CLDZ0G-caQ27skpiXukBXpNezYaPhw",
            "source": "youtube",
            "added_date": "2026-04-16T16:52:04.464408Z"
        },
        {
            "id": "epRyUAXWo9k",
            "title": "NEW HD RESTORATIONđźŤ• Target Earth (1954) COLD WAR SCI-FIđźŤ• FULL MOVIE",
            "url": "https://www.youtube.com/watch?v=epRyUAXWo9k",
            "duration": 4523.0,
            "view_count": 191744,
            "uploader": "PizzaFlix",
            "category": "scifi",
            "channel_tags": [
                "classic",
                "noir",
                "western"
            ],
            "channel_name": "PizzaFlix",
            "thumbnail": "https://i.ytimg.com/vi/epRyUAXWo9k/hqdefault.jpg?sqp=-oaymwEcCNACELwBSFXyq4qpAw4IARUAAIhCGAFwAcABBg==&rs=AOn4CLB-ZhGUqKZtnpljkuK4ZI5ueKIWmg",
            "source": "youtube",
            "added_date": "2026-04-16T16:52:04.665034Z"
        },
        {
            "id": "dRxqyc-qsy4",
            "title": "Anna Christie (MGM, 1930) GARBO TALKSđźŤ• OSCAR NOMINEEđźŤ• FULL MOVIE",
            "url": "https://www.youtube.com/watch?v=dRxqyc-qsy4",
            "duration": 5448.0,
            "view_count": 8767,
            "uploader": "PizzaFlix",
            "category": "classic",
            "channel_tags": [
                "classic",
                "noir",
                "western"
            ],
            "channel_name": "PizzaFlix",
            "thumbnail": "https://i.ytimg.com/vi/dRxqyc-qsy4/hqdefault.jpg?sqp=-oaymwEcCNACELwBSFXyq4qpAw4IARUAAIhCGAFwAcABBg==&rs=AOn4CLC8FYp41ZWq3VoaO5OmA0BUP5duQg",
            "source": "youtube",
            "added_date": "2026-04-16T16:52:04.870140Z"
        },
        {
            "id": "W8FL8W5e2eo",
            "title": "The Divorcee (MGM, 1930) OSCAR WINNERđźŤ• NORMA SHEARER",
            "url": "https://www.youtube.com/watch?v=W8FL8W5e2eo",
            "duration": 5015.0,
            "view_count": 18700,
            "uploader": "PizzaFlix",
            "category": "classic",
            "channel_tags": [
                "classic",
                "noir",
                "western"
            ],
            "channel_name": "PizzaFlix",
            "thumbnail": "https://i.ytimg.com/vi/W8FL8W5e2eo/hqdefault.jpg?sqp=-oaymwEcCNACELwBSFXyq4qpAw4IARUAAIhCGAFwAcABBg==&rs=AOn4CLB7LegmD_f7W6yItlcC53nl4Bd46A",
            "source": "youtube",
            "added_date": "2026-04-16T16:52:05.074508Z"
        },
        {
            "id": "LaqiHiGd_C8",
            "title": "The Bishop Murder Case (MGM, 1930) BASIL RATHBONEđźŤ• PHILO VANCEđźŤ• FULL MOVIE MYSTERY",
            "url": "https://www.youtube.com/watch?v=LaqiHiGd_C8",
            "duration": 5321.0,
            "view_count": 41598,
            "uploader": "PizzaFlix",
            "category": "classic",
            "channel_tags": [
                "classic",
                "noir",
                "western"
            ],
            "channel_name": "PizzaFlix",
            "thumbnail": "https://i.ytimg.com/vi/LaqiHiGd_C8/hqdefault.jpg?sqp=-oaymwEcCNACELwBSFXyq4qpAw4IARUAAIhCGAFwAcABBg==&rs=AOn4CLAs_HpOZ14u6Cq4tfhvvJSuNngL_g",
            "source": "youtube",
            "added_date": "2026-04-16T16:52:05.279673Z"
        },
        {
            "id": "3QLmRq-qlj0",
            "title": "NEW HD RESTORATION đźŤ• The Trollenberg Terror (1958) aka THE CRAWLING EYE",
            "url": "https://www.youtube.com/watch?v=3QLmRq-qlj0",
            "duration": 5046.0,
            "view_count": 159974,
            "uploader": "PizzaFlix",
            "category": "classic",
            "channel_tags": [
                "classic",
                "noir",
                "western"
            ],
            "channel_name": "PizzaFlix",
            "thumbnail": "https://i.ytimg.com/vi/3QLmRq-qlj0/hqdefault.jpg?sqp=-oaymwEcCNACELwBSFXyq4qpAw4IARUAAIhCGAFwAcABBg==&rs=AOn4CLDqYrYjR508rEUwcVx1E2k-874kjA",
            "source": "youtube",
            "added_date": "2026-04-16T16:52:05.484814Z"
        },
        {
            "id": "Bc7rvKHUWa0",
            "title": "The Texan (1930) GARY COOPERđźŤ• FAY WRAY đźŤ• FULL MOVIE WESTERN",
            "url": "https://www.youtube.com/watch?v=Bc7rvKHUWa0",
            "duration": 4829.0,
            "view_count": 51537,
            "uploader": "PizzaFlix",
            "category": "western",
            "channel_tags": [
                "classic",
                "noir",
                "western"
            ],
            "channel_name": "PizzaFlix",
            "thumbnail": "https://i.ytimg.com/vi/Bc7rvKHUWa0/hqdefault.jpg?sqp=-oaymwEcCNACELwBSFXyq4qpAw4IARUAAIhCGAFwAcABBg==&rs=AOn4CLBWfG4pZh8nl56mt1vfr1PnBq2rFQ",
            "source": "youtube",
            "added_date": "2026-04-16T16:52:05.689920Z"
        },
        {
            "id": "G8OVk0cPP8k",
            "title": "White Zombie | FULL MOVIE | Bela Lugosi | B&W Zombies Cult Horror",
            "url": "https://www.youtube.com/watch?v=G8OVk0cPP8k",
            "duration": 4067.0,
            "view_count": 1595,
            "uploader": "Shout Studios",
            "category": "horror",
            "channel_tags": [
                "action",
                "classic",
                "comedy"
            ],
            "channel_name": "Shout Studios",
            "thumbnail": "https://i.ytimg.com/vi/G8OVk0cPP8k/hqdefault.jpg?sqp=-oaymwEcCNACELwBSFXyq4qpAw4IARUAAIhCGAFwAcABBg==&rs=AOn4CLD_cejcgU6E7OSpGWIQiKgac_LH0w",
            "source": "youtube",
            "added_date": "2026-04-16T16:52:08.541251Z"
        },
        {
            "id": "KTBPpdFyQNQ",
            "title": "Undead | 2003 | FULL MOVIE | Zombies Horror Action Comedy Fantasy Sci-Fi",
            "url": "https://www.youtube.com/watch?v=KTBPpdFyQNQ",
            "duration": 5800.0,
            "view_count": 7112,
            "uploader": "Shout Studios",
            "category": "horror",
            "channel_tags": [
                "action",
                "classic",
                "comedy"
            ],
            "channel_name": "Shout Studios",
            "thumbnail": "https://i.ytimg.com/vi/KTBPpdFyQNQ/hqdefault.jpg?sqp=-oaymwEcCNACELwBSFXyq4qpAw4IARUAAIhCGAFwAcABBg==&rs=AOn4CLBLIKvs2dMavpTWFOQIoigS1zaZSQ",
            "source": "youtube",
            "added_date": "2026-04-16T16:52:08.746333Z"
        },
        {
            "id": "qnCRLHA5egQ",
            "title": "Last Plane Out | FULL MOVIE | Jan-Michael Vincent | War Action Rebels Thriller",
            "url": "https://www.youtube.com/watch?v=qnCRLHA5egQ",
            "duration": 5808.0,
            "view_count": 4486,
            "uploader": "Shout Studios",
            "category": "thriller",
            "channel_tags": [
                "action",
                "classic",
                "comedy"
            ],
            "channel_name": "Shout Studios",
            "thumbnail": "https://i.ytimg.com/vi/qnCRLHA5egQ/hqdefault.jpg?sqp=-oaymwEcCNACELwBSFXyq4qpAw4IARUAAIhCGAFwAcABBg==&rs=AOn4CLAkBJb8o3rSbyDW1TDGBinekD7m-g",
            "source": "youtube",
            "added_date": "2026-04-16T16:52:08.947136Z"
        },
        {
            "id": "KIyVi1qePXo",
            "title": "The Corsican Brothers | FULL MOVIE | Douglas Fairbanks Jr. | B&W Swords Adventure",
            "url": "https://www.youtube.com/watch?v=KIyVi1qePXo",
            "duration": 6677.0,
            "view_count": 14463,
            "uploader": "Shout Studios",
            "category": "action",
            "channel_tags": [
                "action",
                "classic",
                "comedy"
            ],
            "channel_name": "Shout Studios",
            "thumbnail": "https://i.ytimg.com/vi/KIyVi1qePXo/hqdefault.jpg?sqp=-oaymwEcCNACELwBSFXyq4qpAw4IARUAAIhCGAFwAcABBg==&rs=AOn4CLDWNtNaeSqXj1uayyO7-lVoaEcZTw",
            "source": "youtube",
            "added_date": "2026-04-16T16:52:09.148121Z"
        },
        {
            "id": "Y1me7gWJ8cs",
            "title": "Sector 7 | FULL MOVIE | Sea Monster Korean Action Horror",
            "url": "https://www.youtube.com/watch?v=Y1me7gWJ8cs",
            "duration": 4875.0,
            "view_count": 10968,
            "uploader": "Shout Studios",
            "category": "horror",
            "channel_tags": [
                "action",
                "classic",
                "comedy"
            ],
            "channel_name": "Shout Studios",
            "thumbnail": "https://i.ytimg.com/vi/Y1me7gWJ8cs/hqdefault.jpg?sqp=-oaymwEcCNACELwBSFXyq4qpAw4IARUAAIhCGAFwAcABBg==&rs=AOn4CLAp_iRpe5PbHYTSFVkw3cPFQ9MK7A",
            "source": "youtube",
            "added_date": "2026-04-16T16:52:09.352691Z"
        },
        {
            "id": "a3BNmv20sZ8",
            "title": "Magic Voyage Of Sinbad | FULL MOVIE | Sword & Sorcery Fantasy Adventure MST3K WTF",
            "url": "https://www.youtube.com/watch?v=a3BNmv20sZ8",
            "duration": 4698.0,
            "view_count": 25781,
            "uploader": "Shout Studios",
            "category": "action",
            "channel_tags": [
                "action",
                "classic",
                "comedy"
            ],
            "channel_name": "Shout Studios",
            "thumbnail": "https://i.ytimg.com/vi/a3BNmv20sZ8/hqdefault.jpg?sqp=-oaymwEcCNACELwBSFXyq4qpAw4IARUAAIhCGAFwAcABBg==&rs=AOn4CLD7aqwwz8frf3ZC16pIWAu6trioQA",
            "source": "youtube",
            "added_date": "2026-04-16T16:52:09.557816Z"
        },
        {
            "id": "846hc_n7F6M",
            "title": "The Messenger | 1986 | FULL MOVIE | Fred Williamson, Cameron Mitchell | Green Beret Revenge Action",
            "url": "https://www.youtube.com/watch?v=846hc_n7F6M",
            "duration": 5836.0,
            "view_count": 1222,
            "uploader": "Shout Studios",
            "category": "action",
            "channel_tags": [
                "action",
                "classic",
                "comedy"
            ],
            "channel_name": "Shout Studios",
            "thumbnail": "https://i.ytimg.com/vi/846hc_n7F6M/hqdefault.jpg?sqp=-oaymwEcCNACELwBSFXyq4qpAw4IARUAAIhCGAFwAcABBg==&rs=AOn4CLCHawFSwRL1gRMZVFXKS9s34CIVpg",
            "source": "youtube",
            "added_date": "2026-04-16T16:52:09.760135Z"
        },
        {
            "id": "___1aNS5EvY",
            "title": "The Deadly Companions | FULL MOVIE | Sam Peckinpah, Maureen O'Hara | Western Action Adventure",
            "url": "https://www.youtube.com/watch?v=___1aNS5EvY",
            "duration": 5588.0,
            "view_count": 3602,
            "uploader": "Shout Studios",
            "category": "western",
            "channel_tags": [
                "action",
                "classic",
                "comedy"
            ],
            "channel_name": "Shout Studios",
            "thumbnail": "https://i.ytimg.com/vi/___1aNS5EvY/hqdefault.jpg?sqp=-oaymwEcCNACELwBSFXyq4qpAw4IARUAAIhCGAFwAcABBg==&rs=AOn4CLBtPuNQvSvk2UGe2AbksP78sQWgIA",
            "source": "youtube",
            "added_date": "2026-04-16T16:52:09.964574Z"
        },
        {
            "id": "Ku4U3qqyB5o",
            "title": "The 39 Steps | 1959 | FULL MOVIE | Kenneth More | British Spy Crime Mystery Thriller",
            "url": "https://www.youtube.com/watch?v=Ku4U3qqyB5o",
            "duration": 5471.0,
            "view_count": 18411,
            "uploader": "Shout Studios",
            "category": "thriller",
            "channel_tags": [
                "action",
                "classic",
                "comedy"
            ],
            "channel_name": "Shout Studios",
            "thumbnail": "https://i.ytimg.com/vi/Ku4U3qqyB5o/hqdefault.jpg?sqp=-oaymwEcCNACELwBSFXyq4qpAw4IARUAAIhCGAFwAcABBg==&rs=AOn4CLBtzrI0AltQf4LAM3EvTLXgz-XMAQ",
            "source": "youtube",
            "added_date": "2026-04-16T16:52:10.169325Z"
        },
        {
            "id": "XaaUyj8QlgA",
            "title": "A Piece Of Cake | FULL MOVIE | Family Fantasy Animation Adventure",
            "url": "https://www.youtube.com/watch?v=XaaUyj8QlgA",
            "duration": 4684.0,
            "view_count": 10482,
            "uploader": "Shout Studios",
            "category": "drama",
            "channel_tags": [
                "action",
                "classic",
                "comedy"
            ],
            "channel_name": "Shout Studios",
            "thumbnail": "https://i.ytimg.com/vi/XaaUyj8QlgA/hqdefault.jpg?sqp=-oaymwEcCNACELwBSFXyq4qpAw4IARUAAIhCGAFwAcABBg==&rs=AOn4CLD1HEZFz_mmX113zyJ4deWzsBGX-Q",
            "source": "youtube",
            "added_date": "2026-04-16T16:52:10.372378Z"
        },
        {
            "id": "dmhIbqzsr-k",
            "title": "On The 3rd Day | FULL MOVIE | Horror Thriller Mystery",
            "url": "https://www.youtube.com/watch?v=dmhIbqzsr-k",
            "duration": 5087.0,
            "view_count": 7483,
            "uploader": "Shout Studios",
            "category": "horror",
            "channel_tags": [
                "action",
                "classic",
                "comedy"
            ],
            "channel_name": "Shout Studios",
            "thumbnail": "https://i.ytimg.com/vi/dmhIbqzsr-k/hqdefault.jpg?sqp=-oaymwEcCNACELwBSFXyq4qpAw4IARUAAIhCGAFwAcABBg==&rs=AOn4CLClTsR0fINlThCpLt7-347IyuFEJw",
            "source": "youtube",
            "added_date": "2026-04-16T16:52:10.577497Z"
        },
        {
            "id": "3DGHgoGmSyc",
            "title": "Man Friday | FULL MOVIE | Peter O'Toole, Richard Roundtree | Shipwrecked Island Adventure Drama",
            "url": "https://www.youtube.com/watch?v=3DGHgoGmSyc",
            "duration": 6615.0,
            "view_count": 12932,
            "uploader": "Shout Studios",
            "category": "drama",
            "channel_tags": [
                "action",
                "classic",
                "comedy"
            ],
            "channel_name": "Shout Studios",
            "thumbnail": "https://i.ytimg.com/vi/3DGHgoGmSyc/hqdefault.jpg?sqp=-oaymwEcCNACELwBSFXyq4qpAw4IARUAAIhCGAFwAcABBg==&rs=AOn4CLDu3k2krBTLMaUv0sinoONMfzziYg",
            "source": "youtube",
            "added_date": "2026-04-16T16:52:10.782609Z"
        },
        {
            "id": "c5QB6gFt5W4",
            "title": "The Man Who Knew Too Much | FULL MOVIE | Alfred Hitchcock, Peter Lorre | B&W Crime Mystery",
            "url": "https://www.youtube.com/watch?v=c5QB6gFt5W4",
            "duration": 4566.0,
            "view_count": 21868,
            "uploader": "Shout Studios",
            "category": "action",
            "channel_tags": [
                "action",
                "classic",
                "comedy"
            ],
            "channel_name": "Shout Studios",
            "thumbnail": "https://i.ytimg.com/vi/c5QB6gFt5W4/hqdefault.jpg?sqp=-oaymwEcCNACELwBSFXyq4qpAw4IARUAAIhCGAFwAcABBg==&rs=AOn4CLCCc8UmGQSvm8oS_d9sEthnQqP7dA",
            "source": "youtube",
            "added_date": "2026-04-16T16:52:10.986820Z"
        },
        {
            "id": "cWFYBfkmLI8",
            "title": "One-Eyed Jacks | FULL MOVIE | Marlon Brando, Slim Pickens | Western Drama",
            "url": "https://www.youtube.com/watch?v=cWFYBfkmLI8",
            "duration": 8468.0,
            "view_count": 34636,
            "uploader": "Shout Studios",
            "category": "drama",
            "channel_tags": [
                "action",
                "classic",
                "comedy"
            ],
            "channel_name": "Shout Studios",
            "thumbnail": "https://i.ytimg.com/vi/cWFYBfkmLI8/hqdefault.jpg?sqp=-oaymwEcCNACELwBSFXyq4qpAw4IARUAAIhCGAFwAcABBg==&rs=AOn4CLBcAGohW72_EHDMcSYRxp7deZ_Wbg",
            "source": "youtube",
            "added_date": "2026-04-16T16:52:11.188437Z"
        },
        {
            "id": "BhD__B1uRKI",
            "title": "The Curse Of King Tut's Tomb | PART 2 of 2 | FULL MOVIE | Casper Van Dien, Malcolm McDowell",
            "url": "https://www.youtube.com/watch?v=BhD__B1uRKI",
            "duration": 5117.0,
            "view_count": 3818,
            "uploader": "Shout Studios",
            "category": "action",
            "channel_tags": [
                "action",
                "classic",
                "comedy"
            ],
            "channel_name": "Shout Studios",
            "thumbnail": "https://i.ytimg.com/vi/BhD__B1uRKI/hqdefault.jpg?sqp=-oaymwEcCNACELwBSFXyq4qpAw4IARUAAIhCGAFwAcABBg==&rs=AOn4CLCMffYfddzBdiwx5wetMvwMr83ChA",
            "source": "youtube",
            "added_date": "2026-04-16T16:52:11.389961Z"
        },
        {
            "id": "KtffVwePPlI",
            "title": "The Curse Of King Tut's Tomb | PART 1 of 2 | FULL MOVIE | Casper Van Dien, Malcolm McDowell",
            "url": "https://www.youtube.com/watch?v=KtffVwePPlI",
            "duration": 5111.0,
            "view_count": 10101,
            "uploader": "Shout Studios",
            "category": "action",
            "channel_tags": [
                "action",
                "classic",
                "comedy"
            ],
            "channel_name": "Shout Studios",
            "thumbnail": "https://i.ytimg.com/vi/KtffVwePPlI/hqdefault.jpg?sqp=-oaymwEcCNACELwBSFXyq4qpAw4IARUAAIhCGAFwAcABBg==&rs=AOn4CLCaUzLbjepmYCqcbBrRG-PM_pExoA",
            "source": "youtube",
            "added_date": "2026-04-16T16:52:11.594879Z"
        },
        {
            "id": "R7qObbWzQAU",
            "title": "The Hitch-Hiker | FULL MOVIE | B&W Crime Cult Film Noir Thriller",
            "url": "https://www.youtube.com/watch?v=R7qObbWzQAU",
            "duration": 4246.0,
            "view_count": 1990,
            "uploader": "Shout Studios",
            "category": "thriller",
            "channel_tags": [
                "action",
                "classic",
                "comedy"
            ],
            "channel_name": "Shout Studios",
            "thumbnail": "https://i.ytimg.com/vi/R7qObbWzQAU/hqdefault.jpg?sqp=-oaymwEcCNACELwBSFXyq4qpAw4IARUAAIhCGAFwAcABBg==&rs=AOn4CLAgjBFom02hwamZC6eHyZWYVnQ28w",
            "source": "youtube",
            "added_date": "2026-04-16T16:52:11.799410Z"
        },
        {
            "id": "YVE7PE3caYQ",
            "title": "Queen Of The Stardust Ballroom | FULL MOVIE | Maureen Stapleton, Charles Durning | Romance Drama",
            "url": "https://www.youtube.com/watch?v=YVE7PE3caYQ",
            "duration": 5865.0,
            "view_count": 3757,
            "uploader": "Shout Studios",
            "category": "drama",
            "channel_tags": [
                "action",
                "classic",
                "comedy"
            ],
            "channel_name": "Shout Studios",
            "thumbnail": "https://i.ytimg.com/vi/YVE7PE3caYQ/hqdefault.jpg?sqp=-oaymwEcCNACELwBSFXyq4qpAw4IARUAAIhCGAFwAcABBg==&rs=AOn4CLDJi8N5RR0BFJNHGbclNU6z2Hv5Dw",
            "source": "youtube",
            "added_date": "2026-04-16T16:52:12.003408Z"
        },
        {
            "id": "uF0joohj5Pw",
            "title": "Miss Annie Rooney | FULL MOVIE | Shirley Temple | B&W B Movie Drama",
            "url": "https://www.youtube.com/watch?v=uF0joohj5Pw",
            "duration": 5172.0,
            "view_count": 18675,
            "uploader": "Shout Studios",
            "category": "drama",
            "channel_tags": [
                "action",
                "classic",
                "comedy"
            ],
            "channel_name": "Shout Studios",
            "thumbnail": "https://i.ytimg.com/vi/uF0joohj5Pw/hqdefault.jpg?sqp=-oaymwEcCNACELwBSFXyq4qpAw4IARUAAIhCGAFwAcABBg==&rs=AOn4CLCG19FjxbdObpjM1D_Zs6HWT-ioJg",
            "source": "youtube",
            "added_date": "2026-04-16T16:52:12.208507Z"
        },
        {
            "id": "uLvFRfQ6seM",
            "title": "Shrooms | FULL MOVIE | Mushrooms Slasher Drugs Horror Mystery Comedy",
            "url": "https://www.youtube.com/watch?v=uLvFRfQ6seM",
            "duration": 5204.0,
            "view_count": 3444,
            "uploader": "Shout Studios",
            "category": "horror",
            "channel_tags": [
                "action",
                "classic",
                "comedy"
            ],
            "channel_name": "Shout Studios",
            "thumbnail": "https://i.ytimg.com/vi/uLvFRfQ6seM/hqdefault.jpg?sqp=-oaymwEcCNACELwBSFXyq4qpAw4IARUAAIhCGAFwAcABBg==&rs=AOn4CLCWukUDyn0zPRoysRUmZTFf0kwPEg",
            "source": "youtube",
            "added_date": "2026-04-16T16:52:12.412880Z"
        },
        {
            "id": "eIlTmsvoVW8",
            "title": "The Pumaman | FULL MOVIE | Donald Pleasence | Superhero Adventure Fantasy MST3K WTF Action",
            "url": "https://www.youtube.com/watch?v=eIlTmsvoVW8",
            "duration": 5807.0,
            "view_count": 4023,
            "uploader": "Shout Studios",
            "category": "action",
            "channel_tags": [
                "action",
                "classic",
                "comedy"
            ],
            "channel_name": "Shout Studios",
            "thumbnail": "https://i.ytimg.com/vi/eIlTmsvoVW8/hqdefault.jpg?sqp=-oaymwEcCNACELwBSFXyq4qpAw4IARUAAIhCGAFwAcABBg==&rs=AOn4CLAxOnYdM6gzGJjAP43L1HOPlsqAsA",
            "source": "youtube",
            "added_date": "2026-04-16T16:52:12.617993Z"
        },
        {
            "id": "SwwO1D3-vRw",
            "title": "Frankenstein Meets The Space Monster | FULL MOVIE | B&W Horror Sci-Fi WTF",
            "url": "https://www.youtube.com/watch?v=SwwO1D3-vRw",
            "duration": 4572.0,
            "view_count": 24497,
            "uploader": "Shout Studios",
            "category": "horror",
            "channel_tags": [
                "action",
                "classic",
                "comedy"
            ],
            "channel_name": "Shout Studios",
            "thumbnail": "https://i.ytimg.com/vi/SwwO1D3-vRw/hqdefault.jpg?sqp=-oaymwEcCNACELwBSFXyq4qpAw4IARUAAIhCGAFwAcABBg==&rs=AOn4CLAt_IO4XQ3C128lC8Ka23zSLgQ0_Q",
            "source": "youtube",
            "added_date": "2026-04-16T16:52:12.819189Z"
        },
        {
            "id": "nB1fE0gQu2U",
            "title": "Echoes From A Somber Empire | FULL MOVIE | Werner Herzog | Bokassa Biography Documentary",
            "url": "https://www.youtube.com/watch?v=nB1fE0gQu2U",
            "duration": 5386.0,
            "view_count": 1231,
            "uploader": "Shout Studios",
            "category": "documentary",
            "channel_tags": [
                "action",
                "classic",
                "comedy"
            ],
            "channel_name": "Shout Studios",
            "thumbnail": "https://i.ytimg.com/vi/nB1fE0gQu2U/hqdefault.jpg?sqp=-oaymwEcCNACELwBSFXyq4qpAw4IARUAAIhCGAFwAcABBg==&rs=AOn4CLBPyxsLuY6A2AWAn5UlnqjYh5QnqA",
            "source": "youtube",
            "added_date": "2026-04-16T16:52:13.024291Z"
        },
        {
            "id": "Nf1PBcqtJCI",
            "title": "Day Of The Dead 2: Contagium | FULL MOVIE | Zombies Horror",
            "url": "https://www.youtube.com/watch?v=Nf1PBcqtJCI",
            "duration": 6210.0,
            "view_count": 8999,
            "uploader": "Shout Studios",
            "category": "horror",
            "channel_tags": [
                "action",
                "classic",
                "comedy"
            ],
            "channel_name": "Shout Studios",
            "thumbnail": "https://i.ytimg.com/vi/Nf1PBcqtJCI/hqdefault.jpg?sqp=-oaymwEcCNACELwBSFXyq4qpAw4IARUAAIhCGAFwAcABBg==&rs=AOn4CLBUIFOrsJk2UryfiC7m6Vx8ZeC9NA",
            "source": "youtube",
            "added_date": "2026-04-16T16:52:13.225966Z"
        },
        {
            "id": "uajCwvbfeAc",
            "title": "Horror Express | FULL MOVIE | Christopher Lee, Peter Cushing, Telly Savalas | Sci-Fi Horror WTF",
            "url": "https://www.youtube.com/watch?v=uajCwvbfeAc",
            "duration": 5263.0,
            "view_count": 7458,
            "uploader": "Shout Studios",
            "category": "horror",
            "channel_tags": [
                "action",
                "classic",
                "comedy"
            ],
            "channel_name": "Shout Studios",
            "thumbnail": "https://i.ytimg.com/vi/uajCwvbfeAc/hqdefault.jpg?sqp=-oaymwEcCNACELwBSFXyq4qpAw4IARUAAIhCGAFwAcABBg==&rs=AOn4CLCcDpLbOmRPs-KZ6NnMQU6gvRkfdQ",
            "source": "youtube",
            "added_date": "2026-04-16T16:52:13.428583Z"
        },
        {
            "id": "27-vxe1sB-w",
            "title": "The Farmer's Wife | FULL MOVIE | Alfred Hitchcock | B&W Silent Film Comedy Drama Romance",
            "url": "https://www.youtube.com/watch?v=27-vxe1sB-w",
            "duration": 6710.0,
            "view_count": 1093,
            "uploader": "Shout Studios",
            "category": "comedy",
            "channel_tags": [
                "action",
                "classic",
                "comedy"
            ],
            "channel_name": "Shout Studios",
            "thumbnail": "https://i.ytimg.com/vi/27-vxe1sB-w/hqdefault.jpg?sqp=-oaymwEcCNACELwBSFXyq4qpAw4IARUAAIhCGAFwAcABBg==&rs=AOn4CLAJrRJxvGOGwBqG3mNa9imnTytYdg",
            "source": "youtube",
            "added_date": "2026-04-16T16:52:13.628956Z"
        },
        {
            "id": "iPkqWgvcLsk",
            "title": "I'll Be There | FULL MOVIE | Craig Ferguson, Charlotte Church | Comedy Music Romance",
            "url": "https://www.youtube.com/watch?v=iPkqWgvcLsk",
            "duration": 6317.0,
            "view_count": 23469,
            "uploader": "Shout Studios",
            "category": "comedy",
            "channel_tags": [
                "action",
                "classic",
                "comedy"
            ],
            "channel_name": "Shout Studios",
            "thumbnail": "https://i.ytimg.com/vi/iPkqWgvcLsk/hqdefault.jpg?sqp=-oaymwEcCNACELwBSFXyq4qpAw4IARUAAIhCGAFwAcABBg==&rs=AOn4CLBswWCmOJ2hWqN-gc_zmEYgAVEkUA",
            "source": "youtube",
            "added_date": "2026-04-16T16:52:13.830463Z"
        },
        {
            "id": "RhLF1bzeq3c",
            "title": "Beast From Haunted Cave | FULL MOVIE | B&W Creature Horror Thriller",
            "url": "https://www.youtube.com/watch?v=RhLF1bzeq3c",
            "duration": 3948.0,
            "view_count": 13205,
            "uploader": "Shout Studios",
            "category": "horror",
            "channel_tags": [
                "action",
                "classic",
                "comedy"
            ],
            "channel_name": "Shout Studios",
            "thumbnail": "https://i.ytimg.com/vi/RhLF1bzeq3c/hqdefault.jpg?sqp=-oaymwEcCNACELwBSFXyq4qpAw4IARUAAIhCGAFwAcABBg==&rs=AOn4CLACFlE1CiXkhm30Gso56ikB5v09rQ",
            "source": "youtube",
            "added_date": "2026-04-16T16:52:14.031956Z"
        },
        {
            "id": "Z6cTKzxzXtM",
            "title": "The Wasp Woman | 1959 | FULL MOVIE | Roger Corman | B&W Horror Sci-Fi Transformation",
            "url": "https://www.youtube.com/watch?v=Z6cTKzxzXtM",
            "duration": 3663.0,
            "view_count": 3110,
            "uploader": "Shout Studios",
            "category": "horror",
            "channel_tags": [
                "action",
                "classic",
                "comedy"
            ],
            "channel_name": "Shout Studios",
            "thumbnail": "https://i.ytimg.com/vi/Z6cTKzxzXtM/hqdefault.jpg?sqp=-oaymwEcCNACELwBSFXyq4qpAw4IARUAAIhCGAFwAcABBg==&rs=AOn4CLBtVri5Uf2rT4pqVfGLD76VOAGF4w",
            "source": "youtube",
            "added_date": "2026-04-16T16:52:14.236833Z"
        },
        {
            "id": "xIth_cP1Xc0",
            "title": "A STRANGER IN THE WOODS đźŽ¬ Full Horror Movie đźŽ¬ English HD",
            "url": "https://www.youtube.com/watch?v=xIth_cP1Xc0",
            "duration": 4910.0,
            "view_count": 9628,
            "uploader": "Watch Movies Now",
            "category": "horror",
            "channel_tags": [
                "horror",
                "scifi",
                "thriller"
            ],
            "channel_name": "Watch Movies Now",
            "thumbnail": "https://i.ytimg.com/vi/xIth_cP1Xc0/hqdefault.jpg?sqp=-oaymwEcCNACELwBSFXyq4qpAw4IARUAAIhCGAFwAcABBg==&rs=AOn4CLAJhjfbLIm-7jsVmoDPdcoo6c77gA",
            "source": "youtube",
            "added_date": "2026-04-16T16:52:17.026170Z"
        },
        {
            "id": "6P6eNiqxvpQ",
            "title": "BAD REPUTATION: LIVING HELL đźŽ¬ Full Horror Movie đźŽ¬ English HD",
            "url": "https://www.youtube.com/watch?v=6P6eNiqxvpQ",
            "duration": 2899.0,
            "view_count": 19297,
            "uploader": "Watch Movies Now",
            "category": "horror",
            "channel_tags": [
                "horror",
                "scifi",
                "thriller"
            ],
            "channel_name": "Watch Movies Now",
            "thumbnail": "https://i.ytimg.com/vi/6P6eNiqxvpQ/hqdefault.jpg?sqp=-oaymwEcCNACELwBSFXyq4qpAw4IARUAAIhCGAFwAcABBg==&rs=AOn4CLCkzkWcDEII0PoQo9eijZwyfm5o4Q",
            "source": "youtube",
            "added_date": "2026-04-16T16:52:17.227065Z"
        },
        {
            "id": "4R2X7AwARtQ",
            "title": "BLOOD PUNCH đźŽ¬ Full Horror Movie đźŽ¬ English HD",
            "url": "https://www.youtube.com/watch?v=4R2X7AwARtQ",
            "duration": 4740.0,
            "view_count": 9764,
            "uploader": "Watch Movies Now",
            "category": "horror",
            "channel_tags": [
                "horror",
                "scifi",
                "thriller"
            ],
            "channel_name": "Watch Movies Now",
            "thumbnail": "https://i.ytimg.com/vi/4R2X7AwARtQ/hqdefault.jpg?sqp=-oaymwEcCNACELwBSFXyq4qpAw4IARUAAIhCGAFwAcABBg==&rs=AOn4CLDakM6tduXtIisWbia7ngJVYZgGIQ",
            "source": "youtube",
            "added_date": "2026-04-16T16:52:17.427838Z"
        }
    ]
}