{
  "last_updated": "2026-04-16T15:21:52.991271Z",
  "history": [
    {
      "timestamp": "2026-04-16T15:21:52.991263Z",
      "added": [
        "PyzccmGpn2I",
        "8xYDXqUHjVc",
        "yjLcN0RFYTI",
        "71iglHr3MzE",
        "kaUemcqIQ-k",
        "gFBw2nT5KXA",
        "7826nZGrF40",
        "_LIiu6vUYGk",
        "bjEq3GB7zvg",
        "UinthQCQHYw",
        "RQinquBq338",
        "BrFqD7otI6E",
        "Iv3uFdG6eFg",
        "6NzB6Bq2CAk",
        "4ECxVO2ZTYk",
        "LYr7Vci9tPo",
        "hmu936_lMv8",
        "wbbHk_tg6eE",
        "rKH2l2KPhEg",
        "acFldAIYz-M",
        "ncOr6JSTMlw",
        "EajZhpq5sKA",
        "vmRb-0v5xfI",
        "zomYZpaHoNw",
        "bFWRHrjyTUA",
        "P00CVJ4NCO4",
        "HGKP2vVwcDg",
        "M_NDLUGQtjI",
        "b0aB7JtOeRg",
        "8Ser7R8PUy8",
        "h94wDfzKkos",
        "Nz18QfdLXfM",
        "BCiJ_oEZp10",
        "D_FX3vbk5oM",
        "jnJ05TWhngk",
        "HPNwWfPiGKQ",
        "gFiptJvLsk4",
        "4E8e2uaKMGE",
        "TkJU90FSh4M",
        "tdFjFGP4kPk",
        "EYJm7hIYLSU",
        "yjpYzFtxfjU",
        "9nK0JcWCk4E",
        "KsrALI7Pxc8",
        "bcMok4PaPEc",
        "EQukgWYC4Hg",
        "FCYQjC4P36c",
        "inF5vSTBRo0",
        "GggCbBYf3RI",
        "4BW2pCTIcv4",
        "CJnD4h6MUAc",
        "GiftA8gDMAA",
        "u-dEnJpCGAQ",
        "LD5ybWHwN3A",
        "cllMdO_lMM0",
        "-uc86VH8hdA",
        "m-QFDir5JcQ",
        "o0RKSFRSI4c",
        "TSRn8BzpvLc",
        "JnQ9EEshnZA",
        "rehNT9wIjUg",
        "CeEO9nRQjHc",
        "7ODYzPni_IE",
        "oVd4yMGxFTE",
        "Ha2r9bRIQko",
        "DpCSHMQzluM",
        "Q62KPR40lbM",
        "MNv2SG9rwTs",
        "UFc4nk8tbqw",
        "LY9-WFwrTP8",
        "q3m9nwWItVg",
        "1BE_QwV87ds",
        "jBNK7vsSUr0",
        "cxyw13C8yDY",
        "e0MdYPY4te0",
        "sbmd6aMyS84",
        "e4aZpA2x7cQ",
        "KxRpAvJ1-Os",
        "sR5n6XaRDKI",
        "fky4KbKHCtY",
        "BCVi0ZshzAE",
        "BAmYhLWA_KE",
        "thTStKBA_gU",
        "oOReBkMrTew",
        "WO1g_ywwcXU",
        "qLeWo3yGMQE",
        "3hfh6zRHhTA",
        "KS_UR6GjhC0",
        "SoH8zfd2lxE",
        "bJMj-5zvZJQ",
        "9lVF83ja0lk",
        "_0Ecqv3qPUw",
        "bOGgDOKtgBA",
        "Ulns8C2bp8U",
        "HccXDZMD-Js",
        "Dz428Fr0YXw",
        "eyRUP3CpcwE",
        "fl9c0X8_0mA",
        "SIvKcv2J6oY",
        "Vp7AY0CL0c4",
        "WwA_7QyqtGI",
        "Iq1bdv5D4YA",
        "X6kPtYOuzeU",
        "Rt6ZwngAhNw",
        "AOm07j3t0Yk",
        "q-omFQLccQM",
        "JTCep-9PZQo",
        "1CpitDfxe-8",
        "4MQZLND5zYw",
        "QeoFgWwGD1Q",
        "NIxmzVli_aY",
        "UBSQaRjW4j8",
        "OoDcbOG07RQ",
        "WbV4bE75FbM",
        "AXSOy4Ckaik",
        "mCjTW9a7Gys",
        "ws8bvXA6Xxw",
        "ML8B04PaYt0",
        "R2FQBr_lQMo"
      ],
      "added_count": 119
    }
  ]
}